{ "_id" : { "$oid" : "537eccdcd59b97b52419f4e4" }, "updated_at" : { "$date" : "2014-05-23T01:21:48.586-0300" }, "created_at" : { "$date" : "2014-05-23T01:21:48.586-0300" }, "fields" : [ { "key" : "video_link", "value" : "//www.youtube.com/embed/lchkOT3IIs4" }, { "key" : "image", "value" : "58eaf0df3472041a5993da96bff09387/12968-x61mmb.jpg" } ], "key" : "top", "__v" : 38 }
{ "_id" : { "$oid" : "537fe0c0e45c19df18e959c0" }, "updated_at" : { "$date" : "2014-05-23T20:58:56.501-0300" }, "created_at" : { "$date" : "2014-05-23T20:58:56.501-0300" }, "fields" : [ { "key" : "text_1", "value" : "A Campanha Eu Quero Minha Biblioteca busca compartilhar informações com gestores públicos  e sociedade civil pela universalização de bibliotecas em escolas." }, { "key" : "text_2", "value" : "Saber ler com gosto e competência é a base para o acesso a todo conhecimento e a biblioteca em escola é o principal meio de acesso gratuito aos livros." }, { "key" : "text_3", "value" : " A universalização das bibliotecas em instituições de ensino públicas e privadas é um direito previsto na lei 12.244/10." }, { "key" : "box_text1", "value" : "* É o principal meio de acesso gratuito ao livro de literatura.\r\n* Causa impacto positivo no rendimento escolar.\r\n* Aumenta o nível de proficiência em leitura.\r\n* Quanto mais perto de uma biblioteca, maior a chance de a criança e o adolescente tornarem-se bons leitores, pois crescem lendo." }, { "key" : "box_text2", "value" : "Em março de 2010, a sanção da Lei 12.244/10 garantiu um direito inalienável: todas as instituições de ensino do país, públicas e privadas, deverão ter biblioteca.\r\nO prazo é 2020.\r\nSua efetividade, portanto, tem de ser tratada como prioridade nacional.\r\nConheça a lei na íntegra: http://presrepublica.jusbrasil.com.br/legislacao/823116/lei-da-biblioteca-escolar-lei-12244-10" }, { "key" : "box_text3", "value" : "* Atuar pela universalização de bibliotecas em escolas.\r\n* Informar gestores públicos sobre como acessar recursos e a importância de construir orçamento para a implantação e manutenção de bibliotecas em escolas.\r\n* Atuar junto à sociedade, direta ou indiretamente, divulgando a importância e os meios para a mobilização cidadã para viabilizar bibliotecas em escolas." }, { "key" : "image", "value" : "e7b4ab1b5d1428da71744d085fd0d6d7/12968-1v80d7r.jpg" } ], "key" : "campaign", "__v" : 7 }
{ "_id" : { "$oid" : "537fe5fefe5ca474565d7bc8" }, "updated_at" : { "$date" : "2014-05-23T21:21:18.776-0300" }, "created_at" : { "$date" : "2014-05-23T21:21:18.776-0300" }, "fields" : [ { "key" : "banner_1", "value" : "51b8b24f319049af3eb8478eefab82f8/3668-xihjma.jpg" }, { "key" : "banner_2", "value" : "f6eab4024cfae2c8c6243d27966eb3ba/3668-e93ivq.jpg" }, { "key" : "banner_3", "value" : "17d8029387f9815a579597975322644a/3668-1hx0zxx.jpg" }, { "key" : "banner_4", "value" : "8ca0a207da62e31b2730b46cfc1f1788/3668-8i0pab.jpg" }, { "key" : "materials", "value" : "30232a7104a95ca6cf428a410f0c80f8/4828-ce72ny.zip" }, { "key" : "banner_5", "value" : "3d61e4d973eceef59976d915d05752d2/4828-12ag71m.jpg" } ], "key" : "share", "__v" : 7 }
{ "_id" : { "$oid" : "537fe98d9b62a0f77e8e82fe" }, "updated_at" : { "$date" : "2014-05-23T21:36:29.286-0300" }, "created_at" : { "$date" : "2014-05-23T21:36:29.286-0300" }, "fields" : [ { "key" : "image", "value" : "28365cabbf634efeb0b65727e1f64941/3886-tmisax.jpg" }, { "key" : "file_orientiations_citizens", "value" : "ebf686039d606cb7388ca5eb70ecb40c/3886-6udrr2.pdf" }, { "key" : "file_orientiations_public_managers", "value" : "35fdaffcc70384bcfcdd46ffba1cd504/3886-1btmxn1.pdf" } ], "key" : "orientations", "__v" : 5 }
{ "_id" : { "$oid" : "53810bd850be0f27294f94fa" }, "updated_at" : { "$date" : "2014-05-24T18:15:04.490-0300" }, "created_at" : { "$date" : "2014-05-24T18:15:04.490-0300" }, "fields" : [ { "key" : "adviser_link_1", "value" : "www.abert.org.br/web/" }, { "key" : "adviser_link_2", "value" : "http://pje.anj.org.br/" }, { "key" : "adviser_image_1", "value" : "634a1d0b34ca66813866c1dcfcd7b8ca/10555-qdd1of.jpg" }, { "key" : "adviser_image_2", "value" : "22f8747a863415c153eda3026cb8d329/10555-skltk4.jpg" } ], "key" : "advisers", "__v" : 3 }
{ "_id" : { "$oid" : "53810e725b5e1d3b29437a7f" }, "updated_at" : { "$date" : "2014-05-24T18:26:10.625-0300" }, "created_at" : { "$date" : "2014-05-24T18:26:10.625-0300" }, "fields" : [ { "key" : "coalizador_link_1", "value" : "http://www.academia.org.br/abl/cgi/cgilua.exe/sys/start.htm?tpl=home" }, { "key" : "coalizador_link_2", "value" : "http://www.cfb.org.br/" }, { "key" : "coalizador_link_3", "value" : "http://www.fnlij.org.br/" }, { "key" : "coalizador_link_4", "value" : "http://senna.globo.com/institutoayrtonsenna/home/index.asp" }, { "key" : "coalizador_link_5", "value" : "http://www.institutocea.org.br/" }, { "key" : "coalizador_link_6", "value" : "http://www.icebrasil.org.br/wordpress/" }, { "key" : "coalizador_link_7", "value" : "http://www2.brasilliterario.org.br/pt/home" }, { "key" : "coalizador_link_8", "value" : "http://www.solmarista.org.br/" }, { "key" : "coalizador_link_9", "value" : "http://www.todospelaeducacao.org.br/" }, { "key" : "coalizador_image_1", "value" : "e6a6f32086396466846cd7a5e1804f18/10555-1qfsaow.jpg" }, { "key" : "coalizador_image_2", "value" : "bd5ea1692303a3578fcc107ad9a59eca/10555-1qw18nf.jpg" }, { "key" : "coalizador_image_3", "value" : "a7bdec6323036d849298c2e032d4b69f/10555-4k16w6.jpg" }, { "key" : "coalizador_image_5", "value" : "5485bdb2f247dc6c90eb6f74eb0d37bd/10555-pv6qi5.jpg" }, { "key" : "coalizador_image_6", "value" : "51b30e59fc4bdaf1c628778e3d89adef/10555-mhysuf.jpg" }, { "key" : "coalizador_image_7", "value" : "78823f1e53367f3f873eaecdaeb4063c/10555-1irbkaa.jpg" }, { "key" : "coalizador_image_8", "value" : "09357e6117205f73b66897da9f1abce1/10555-10w2yxc.jpg" }, { "key" : "coalizador_image_9", "value" : "512f7721dc33eaa5ca60d2a3fa1abd21/10555-jkv742.jpg" }, { "key" : "coalizador_image_4", "value" : "6b7a578ae691175193e740c6e259ddba/10555-1fioyy3.jpg" } ], "key" : "coalizadores", "__v" : 1 }
{ "_id" : { "$oid" : "53810f1a5b5e1d3b29437a83" }, "updated_at" : { "$date" : "2014-05-24T18:28:58.683-0300" }, "created_at" : { "$date" : "2014-05-24T18:28:58.683-0300" }, "fields" : [ { "key" : "sponsor_link_1", "value" : "http://valmet.com/" }, { "key" : "sponsor_link_2", "value" : "" }, { "key" : "sponsor_image_1", "value" : "1018b4dc27494f714cba1b4e7b4a88af/10555-j1c508.jpg" }, { "key" : "sponsor_image_2", "value" : "" } ], "key" : "sponsors", "__v" : 2 }
